geopyv-0.0.31.data/data/CMakeLists.txt
geopyv-0.0.31.data/data/Pipfile
geopyv-0.0.31.data/data/LICENSE
geopyv-0.0.31.data/data/basictest.py
geopyv-0.0.31.data/data/.gitignore
geopyv-0.0.31.data/data/Pipfile.lock
geopyv-0.0.31.data/data/README.md
geopyv-0.0.31.data/data/.gitmodules
geopyv.libs/libgomp-d22c30c5.so.1.0.0
geopyv/object.py
geopyv/calibration.py
geopyv/log.py
geopyv/speckle.py
geopyv/image.py
geopyv/plots.py
geopyv/_subset_extensions.cpython-310-aarch64-linux-gnu.so
geopyv/sequence.py
geopyv/__init__.py
geopyv/validation.py
geopyv/field.py
geopyv/subset.py
geopyv/check.py
geopyv/particle.py
geopyv/mesh.py
geopyv/io.py
geopyv/templates.py
geopyv/_image_extensions.cpython-310-aarch64-linux-gnu.so
geopyv/include/eigen3/signature_of_eigen3_matrix_library
geopyv/include/eigen3/unsupported/Eigen/EulerAngles
geopyv/include/eigen3/unsupported/Eigen/OpenGLSupport
geopyv/include/eigen3/unsupported/Eigen/BVH
geopyv/include/eigen3/unsupported/Eigen/FFT
geopyv/include/eigen3/unsupported/Eigen/KroneckerProduct
geopyv/include/eigen3/unsupported/Eigen/AlignedVector3
geopyv/include/eigen3/unsupported/Eigen/LevenbergMarquardt
geopyv/include/eigen3/unsupported/Eigen/MatrixFunctions
geopyv/include/eigen3/unsupported/Eigen/MoreVectorization
geopyv/include/eigen3/unsupported/Eigen/NumericalDiff
geopyv/include/eigen3/unsupported/Eigen/MPRealSupport
geopyv/include/eigen3/unsupported/Eigen/SparseExtra
geopyv/include/eigen3/unsupported/Eigen/AutoDiff
geopyv/include/eigen3/unsupported/Eigen/NNLS
geopyv/include/eigen3/unsupported/Eigen/NonLinearOptimization
geopyv/include/eigen3/unsupported/Eigen/Splines
geopyv/include/eigen3/unsupported/Eigen/SpecialFunctions
geopyv/include/eigen3/unsupported/Eigen/ArpackSupport
geopyv/include/eigen3/unsupported/Eigen/Skyline
geopyv/include/eigen3/unsupported/Eigen/AdolcForward
geopyv/include/eigen3/unsupported/Eigen/Polynomials
geopyv/include/eigen3/unsupported/Eigen/IterativeSolvers
geopyv-0.0.31.dist-info/WHEEL
geopyv-0.0.31.dist-info/LICENSE
geopyv-0.0.31.dist-info/RECORD
geopyv-0.0.31.dist-info/top_level.txt
geopyv-0.0.31.dist-info/METADATA
