Metadata-Version: 2.1
Name: geopyv
Version: 0.0.31
Summary: A PIV/DIC analysis package for Python.
Author-email: Sam Stanier <sas229@cam.ac.uk>, Jonathan Smith <jdks2@cam.ac.uk>
Project-URL: Homepage, https://github.com/sas229/geopyv
Project-URL: Bug Tracker, https://github.com/sas229/geopyv/issues
Classifier: Programming Language :: Python :: 3
Classifier: License :: OSI Approved :: GNU General Public License v3 (GPLv3)
Classifier: Operating System :: POSIX :: Linux
Requires-Python: >=3.7
License-File: LICENSE
Requires-Dist: numpy ==1.23.3
Requires-Dist: opencv-python ==4.7.0.68
Requires-Dist: opencv-contrib-python ==4.7.0.68
Requires-Dist: matplotlib ==3.6.3
Requires-Dist: alive-progress ==3.0.1
Requires-Dist: scipy ==1.10.0
Requires-Dist: gmsh ==4.11.1
Requires-Dist: numpyencoder ==0.3.0
Requires-Dist: pyside6 ==6.4.2
Requires-Dist: pre-commit ==3.0.2
